drf_extensions_django2_patch-0.3.2.dist-info/DESCRIPTION.rst
drf_extensions_django2_patch-0.3.2.dist-info/METADATA
drf_extensions_django2_patch-0.3.2.dist-info/RECORD
drf_extensions_django2_patch-0.3.2.dist-info/WHEEL
drf_extensions_django2_patch-0.3.2.dist-info/metadata.json
drf_extensions_django2_patch-0.3.2.dist-info/top_level.txt
rest_framework_extensions/__init__.py
rest_framework_extensions/compat.py
rest_framework_extensions/compat_drf.py
rest_framework_extensions/exceptions.py
rest_framework_extensions/fields.py
rest_framework_extensions/mixins.py
rest_framework_extensions/models.py
rest_framework_extensions/routers.py
rest_framework_extensions/serializers.py
rest_framework_extensions/settings.py
rest_framework_extensions/test.py
rest_framework_extensions/utils.py
rest_framework_extensions/bulk_operations/__init__.py
rest_framework_extensions/bulk_operations/mixins.py
rest_framework_extensions/cache/__init__.py
rest_framework_extensions/cache/decorators.py
rest_framework_extensions/cache/mixins.py
rest_framework_extensions/etag/__init__.py
rest_framework_extensions/etag/decorators.py
rest_framework_extensions/etag/mixins.py
rest_framework_extensions/key_constructor/__init__.py
rest_framework_extensions/key_constructor/bits.py
rest_framework_extensions/key_constructor/constructors.py
rest_framework_extensions/permissions/__init__.py
rest_framework_extensions/permissions/extended_django_object_permissions.py
