Metadata-Version: 2.0
Name: drf-extensions-django2-patch
Version: 0.3.2
Summary: Extensions for Django REST Framework updated for Django 2.0+
Home-page: http://github.com/programatt/drf-extensions
Author: Gennady Chibisov
Author-email: web-chib@ya.ru
License: BSD
Download-URL: https://pypi.python.org/pypi/drf-extensions/
Platform: UNKNOWN
Classifier: Development Status :: 5 - Production/Stable
Classifier: Environment :: Web Environment
Classifier: Framework :: Django
Classifier: Intended Audience :: Developers
Classifier: License :: OSI Approved :: MIT License
Classifier: Operating System :: OS Independent
Classifier: Programming Language :: Python
Classifier: Programming Language :: Python :: 3
Classifier: Topic :: Internet :: WWW/HTTP
Requires-Dist: djangorestframework (>=3.3.1)
Requires-Dist: django (>=2.0.0)
